{"ast":null,"code":"import { combineReducers } from \"redux\";\nimport entities from \"./entities_reducer\";\nexport default combineReducers({\n  entities: entities\n});","map":{"version":3,"sources":["/Users/carlosgarciajr/Documents/programming/yo_soy_garcia/app/javascript/frontend/reducers/root_reducer.js"],"names":["combineReducers","entities"],"mappings":"AAAA,SAASA,eAAT,QAAgC,OAAhC;AACA,OAAOC,QAAP,MAAqB,oBAArB;AAGA,eAAeD,eAAe,CAAC;AAC7BC,EAAAA,QAAQ,EAARA;AAD6B,CAAD,CAA9B","sourcesContent":["import { combineReducers } from \"redux\";\nimport entities from \"./entities_reducer\";\n\n\nexport default combineReducers({\n  entities\n});\n\n"]},"metadata":{},"sourceType":"module"}